{
    "name": "Company",
    "fields": [
        {
            "fieldName": "name",
            "fieldType": "String"
        },
        {
            "fieldName": "discription",
            "fieldType": "String"
        },
        {
            "fieldName": "tenantId",
            "fieldType": "String"
        }
    ],
    "relationships": [
        {
            "relationshipType": "one-to-many",
            "otherEntityName": "employee",
            "otherEntityRelationshipName": "company",
            "relationshipName": "employee"
        },
        {
            "relationshipName": "inventory",
            "otherEntityName": "inventory",
            "relationshipType": "many-to-one",
            "otherEntityField": "id"
        }
    ],
    "changelogDate": "20200225134414",
    "entityTableName": "company",
    "dto": "mapstruct",
    "pagination": "pagination",
    "service": "serviceClass",
    "jpaMetamodelFiltering": false,
    "fluentMethods": true,
    "clientRootFolder": "",
    "applications": [
        "barLevelService"
    ]
}